LICENSE
MANIFEST.in
Makefile
README.md
dlrepo-cli
pylintrc
requirements-dev.txt
setup.cfg
setup.py
dlrepo/__init__.py
dlrepo/__main__.py
dlrepo.egg-info/PKG-INFO
dlrepo.egg-info/SOURCES.txt
dlrepo.egg-info/dependency_links.txt
dlrepo.egg-info/entry_points.txt
dlrepo.egg-info/not-zip-safe
dlrepo.egg-info/requires.txt
dlrepo.egg-info/top_level.txt
dlrepo/fs/__init__.py
dlrepo/fs/branch.py
dlrepo/fs/container.py
dlrepo/fs/fmt.py
dlrepo/fs/job.py
dlrepo/fs/product.py
dlrepo/fs/tag.py
dlrepo/fs/util.py
dlrepo/static/favicon.svg
dlrepo/static/locked.svg
dlrepo/static/logo.svg
dlrepo/static/published.svg
dlrepo/static/released.svg
dlrepo/templates/autoindex.html
dlrepo/templates/base.html
dlrepo/templates/branch.html
dlrepo/templates/branches.html
dlrepo/templates/home.html
dlrepo/templates/job.html
dlrepo/templates/macros.html
dlrepo/templates/product.html
dlrepo/templates/product_branch.html
dlrepo/templates/product_variant.html
dlrepo/templates/product_version.html
dlrepo/templates/products.html
dlrepo/templates/tag.html
dlrepo/views/__init__.py
dlrepo/views/artifact.py
dlrepo/views/auth.py
dlrepo/views/branch.py
dlrepo/views/container.py
dlrepo/views/errors.py
dlrepo/views/fmt.py
dlrepo/views/job.py
dlrepo/views/product.py
dlrepo/views/tag.py
dlrepo/views/util.py
docs/dlrepo-acls.5.scdoc
docs/dlrepo-api.7.scdoc
docs/dlrepo-cli.1.scdoc
docs/dlrepo-config.5.scdoc
docs/dlrepo-layout.7.scdoc
docs/dlrepo.7.scdoc
etc/default
etc/dlrepo.service
etc/dlrepo.socket
etc/nginx.conf
etc/post-process.sh
scss/components.scss
scss/layout.scss
scss/main.scss
scss/normalize.scss
scss/sections.scss
scss/variables.scss
tests/conftest.py
tests/test_archive.py
tests/test_auth.py
tests/test_auth_headers.py
tests/test_digests.py
tests/test_post_process.py
tests/test_publish.py
tests/test_x_sendfile.py
tests/__pycache__/conftest.cpython-313-pytest-7.4.3.pyc
tests/__pycache__/test_archive.cpython-313-pytest-7.4.3.pyc
tests/__pycache__/test_auth.cpython-313-pytest-7.4.3.pyc
tests/__pycache__/test_auth_headers.cpython-313-pytest-7.4.3.pyc
tests/__pycache__/test_digests.cpython-313-pytest-7.4.3.pyc
tests/__pycache__/test_post_process.cpython-313-pytest-7.4.3.pyc
