Metadata-Version: 2.4
Name: dlrepo
Version: 0.44
Summary: Artifact repository
Home-page: https://sr.ht/~rjarry/dlrepo/
Author: Robin Jarry
Author-email: robin@jarry.cc
License: BSD-3-Clause
License-File: LICENSE
Requires-Dist: aiohttp>=3.8.0
Requires-Dist: aiohttp-jinja2
Requires-Dist: cachetools
Requires-Dist: bonsai
Dynamic: author
Dynamic: author-email
Dynamic: description
Dynamic: description-content-type
Dynamic: home-page
Dynamic: license
Dynamic: license-file
Dynamic: requires-dist
Dynamic: summary
